[
 [
  [
   330245, 
   null, 
   "TTT", 
   "European court ruled that asserts of Iranian terrorists' The People's Mujaheideen Organization should be unfrozen! \n It's original interpretation! Look, organization which realized the acts of terrorism against Muslims in 70-80th of last century isn't considered a terrorist one and its asserts could be unfrozen! I understand that in case of murdering of the white it would be quite a different story! But now this organization has activity in Iran wich is to be attacked by USA soon, that's why Europeans are trying to help to the major ally and that is USA! This is double standards in action! Everything must be for the welfare of USA and if The People's Mujaheideen Organization will put Ahmadinijad out it's not terrifying at all!", 
   {
    "post_info": {
     "post_title": "European court ruled that asserts of Iranian terrorists\u0092..."
    }, 
    "unicode_changes_made": true
   }, 
   null, 
   null, 
   1225299780.0
  ]
 ], 
 {}, 
 {
  "title": "4Forums.com Political Debates and Polls -  European court ruled that asserts of Iranian terrorists\u0092...", 
  "url": "http://www.4forums.com/political/current-events-debates/11861-european-court-ruled-asserts-iranian-terrorists.html", 
  "breadcrumbs": [
   "Current Events"
  ], 
  "id_number": 11861, 
  "discussion_files": [
   [
    "9632.html", 
    "http://www.4forums.com/political/current-events-debates/11861-european-court-ruled-asserts-iranian-terrorists-print.html"
   ]
  ], 
  "identifier": 11861
 }
]