[
 [
  299010, 
  [
   0, 
   59, 
   {
    "raw_data": "jitobear;287548", 
    "quote_id": 287548, 
    "author": "jitobear"
   }
  ]
 ], 
 [
  287247, 
  [
   0, 
   143, 
   {
    "raw_data": "Batman;287141", 
    "quote_id": 287141, 
    "author": "Batman"
   }
  ]
 ], 
 [
  287251, 
  [
   0, 
   143, 
   {
    "raw_data": "Batman;287141", 
    "quote_id": 287141, 
    "author": "Batman"
   }
  ]
 ], 
 [
  299161, 
  [
   194, 
   326, 
   {
    "raw_data": "sinjin;299057", 
    "quote_id": 299057, 
    "author": "sinjin"
   }
  ]
 ], 
 [
  287521, 
  [
   0, 
   311, 
   {
    "raw_data": "snakespit;287520", 
    "quote_id": 287520, 
    "author": "snakespit"
   }
  ]
 ], 
 [
  287141, 
  [
   0, 
   408, 
   {}
  ]
 ], 
 [
  310960, 
  [
   0, 
   662, 
   {
    "raw_data": "CUNxTime;301371", 
    "quote_id": 301371, 
    "author": "CUNxTime"
   }
  ]
 ], 
 [
  299057, 
  [
   0, 
   154, 
   {
    "raw_data": "ironcourage;299010", 
    "quote_id": 299010, 
    "author": "ironcourage"
   }
  ]
 ], 
 [
  287931, 
  [
   0, 
   63, 
   {
    "raw_data": "Winston Smith;287860", 
    "quote_id": 287860, 
    "author": "Winston Smith"
   }
  ]
 ], 
 [
  287548, 
  [
   0, 
   157, 
   {
    "raw_data": "jim's trucking;287534", 
    "quote_id": 287534, 
    "author": "jim's trucking"
   }
  ]
 ], 
 [
  287805, 
  [
   0, 
   59, 
   {
    "raw_data": "jitobear;287548", 
    "quote_id": 287548, 
    "author": "jitobear"
   }
  ]
 ], 
 [
  299086, 
  [
   0, 
   1051, 
   {
    "raw_data": "ironcourage;299010", 
    "quote_id": 299010, 
    "author": "ironcourage"
   }
  ]
 ], 
 [
  313686, 
  [
   0, 
   90, 
   {
    "raw_data": "Ethmi;313528", 
    "quote_id": 313528, 
    "author": "Ethmi"
   }
  ]
 ], 
 [
  299236, 
  [
   0, 
   854, 
   {
    "raw_data": "ironcourage;299161", 
    "quote_id": 299161, 
    "author": "ironcourage"
   }
  ]
 ], 
 [
  287974, 
  [
   0, 
   105, 
   {
    "raw_data": "Batman;287931", 
    "quote_id": 287931, 
    "author": "Batman"
   }
  ]
 ], 
 [
  287852, 
  [
   0, 
   181, 
   {
    "raw_data": "jim's trucking;287805", 
    "quote_id": 287805, 
    "author": "jim's trucking"
   }
  ]
 ], 
 [
  288368, 
  [
   0, 
   91, 
   {
    "raw_data": "sinjin;287974", 
    "quote_id": 287974, 
    "author": "sinjin"
   }
  ]
 ], 
 [
  287859, 
  [
   0, 
   1206, 
   {
    "raw_data": "jitobear;287251", 
    "quote_id": 287251, 
    "author": "jitobear"
   }
  ]
 ], 
 [
  287860, 
  [
   0, 
   143, 
   {
    "raw_data": "Batman;287141", 
    "quote_id": 287141, 
    "author": "Batman"
   }
  ]
 ]
]