[
 [
  62786, 
  [
   0, 
   104, 
   {
    "raw_data": "emclean", 
    "quote_id": 62625, 
    "author": "emclean"
   }
  ]
 ], 
 [
  62632, 
  [
   0, 
   104, 
   {
    "raw_data": "Duo_Maxwell", 
    "author": "Duo_Maxwell"
   }
  ]
 ], 
 [
  62632, 
  [
   144, 
   433, 
   {}
  ]
 ], 
 [
  62632, 
  [
   476, 
   790, 
   {}
  ]
 ], 
 [
  62632, 
  [
   946, 
   1029, 
   {
    "quote_id": 62585, 
    "author": "Duo_Maxwell"
   }
  ]
 ], 
 [
  62632, 
  [
   1071, 
   1307, 
   {
    "quote_id": 62585, 
    "author": "Duo_Maxwell"
   }
  ]
 ], 
 [
  62632, 
  [
   1355, 
   1433, 
   {
    "quote_id": 62585, 
    "author": "Duo_Maxwell"
   }
  ]
 ], 
 [
  62632, 
  [
   1503, 
   2140, 
   {
    "quote_id": 62585, 
    "author": "Duo_Maxwell"
   }
  ]
 ], 
 [
  62632, 
  [
   2249, 
   3025, 
   {}
  ]
 ], 
 [
  62632, 
  [
   3099, 
   4484, 
   {}
  ]
 ], 
 [
  62632, 
  [
   4688, 
   5021, 
   {
    "quote_id": 62585, 
    "author": "Duo_Maxwell"
   }
  ]
 ]
]