[
 [
  99168, 
  [
   0, 
   217, 
   {
    "raw_data": "sinjin", 
    "quote_id": 99050, 
    "author": "sinjin"
   }
  ]
 ], 
 [
  101702, 
  [
   126, 
   337, 
   {
    "quote_id": 98933, 
    "author": "GRINGO"
   }
  ]
 ], 
 [
  101702, 
  [
   645, 
   856, 
   {
    "quote_id": 98933, 
    "author": "GRINGO"
   }
  ]
 ], 
 [
  101702, 
  [
   885, 
   1083, 
   {
    "quote_id": 98933, 
    "author": "GRINGO"
   }
  ]
 ], 
 [
  101702, 
  [
   1393, 
   1750, 
   {
    "quote_id": 98933, 
    "author": "GRINGO"
   }
  ]
 ], 
 [
  101702, 
  [
   1977, 
   2368, 
   {
    "quote_id": 98933, 
    "author": "GRINGO"
   }
  ]
 ], 
 [
  101702, 
  [
   2424, 
   2628, 
   {
    "quote_id": 98933, 
    "author": "GRINGO"
   }
  ]
 ], 
 [
  101702, 
  [
   2802, 
   2941, 
   {
    "quote_id": 98933, 
    "author": "GRINGO"
   }
  ]
 ], 
 [
  99047, 
  [
   0, 
   117, 
   {
    "quote_id": 99023, 
    "author": "GRINGO"
   }
  ]
 ], 
 [
  98938, 
  [
   0, 
   69, 
   {
    "raw_data": "GRINGO", 
    "quote_id": 98933, 
    "author": "GRINGO"
   }
  ]
 ], 
 [
  101726, 
  [
   0, 
   54, 
   {
    "raw_data": "GRINGO", 
    "quote_id": 99023, 
    "author": "GRINGO"
   }
  ]
 ]
]