[
 [
  148227, 
  [
   0, 
   255, 
   {
    "raw_data": "Orion", 
    "quote_id": 148169, 
    "author": "Orion"
   }
  ]
 ], 
 [
  148356, 
  [
   0, 
   634, 
   {
    "raw_data": "Orion", 
    "quote_id": 148169, 
    "author": "Orion"
   }
  ]
 ], 
 [
  148233, 
  [
   0, 
   196, 
   {
    "raw_data": "jazyjason", 
    "quote_id": 148172, 
    "author": "jazyjason"
   }
  ]
 ], 
 [
  148362, 
  [
   0, 
   1294, 
   {
    "raw_data": "Easyrider", 
    "quote_id": 148356, 
    "author": "Easyrider"
   }
  ]
 ], 
 [
  149388, 
  [
   0, 
   383, 
   {
    "raw_data": "jazyjason", 
    "quote_id": 148566, 
    "author": "jazyjason"
   }
  ]
 ], 
 [
  148484, 
  [
   0, 
   59, 
   {
    "raw_data": "Orion", 
    "quote_id": 148426, 
    "author": "Orion"
   }
  ]
 ], 
 [
  148484, 
  [
   134, 
   219, 
   {
    "quote_id": 148426, 
    "author": "Orion"
   }
  ]
 ], 
 [
  150319, 
  [
   0, 
   130, 
   {
    "raw_data": "Jacques", 
    "author": "Jacques"
   }
  ]
 ], 
 [
  150319, 
  [
   473, 
   710, 
   {
    "raw_data": "Jacques", 
    "author": "Jacques"
   }
  ]
 ], 
 [
  152860, 
  [
   39, 
   142, 
   {
    "raw_data": "Easyrider", 
    "quote_id": 152806, 
    "author": "Easyrider"
   }
  ]
 ], 
 [
  148255, 
  [
   0, 
   309, 
   {
    "raw_data": "jyoshu", 
    "quote_id": 148240, 
    "author": "jyoshu"
   }
  ]
 ], 
 [
  152867, 
  [
   0, 
   103, 
   {
    "raw_data": "Easyrider", 
    "quote_id": 152806, 
    "author": "Easyrider"
   }
  ]
 ], 
 [
  150437, 
  [
   0, 
   43, 
   {
    "raw_data": "Dzeron", 
    "quote_id": 150368, 
    "author": "Dzeron"
   }
  ]
 ], 
 [
  148264, 
  [
   0, 
   1799, 
   {
    "raw_data": "Orion", 
    "quote_id": 148169, 
    "author": "Orion"
   }
  ]
 ], 
 [
  149165, 
  [
   0, 
   139, 
   {
    "raw_data": "Orion", 
    "quote_id": 148169, 
    "author": "Orion"
   }
  ]
 ], 
 [
  153007, 
  [
   0, 
   196, 
   {
    "raw_data": "Easyrider", 
    "quote_id": 153006, 
    "author": "Easyrider"
   }
  ]
 ], 
 [
  148407, 
  [
   0, 
   58, 
   {
    "raw_data": "Trebor", 
    "quote_id": 148362, 
    "unknown_author": "Trebor", 
    "author": "trebor"
   }
  ]
 ], 
 [
  148407, 
  [
   212, 
   279, 
   {
    "raw_data": "Trebor", 
    "quote_id": 148362, 
    "unknown_author": "Trebor", 
    "author": "trebor"
   }
  ]
 ], 
 [
  149432, 
  [
   0, 
   114, 
   {
    "raw_data": "Easyrider", 
    "quote_id": 149165, 
    "author": "Easyrider"
   }
  ]
 ], 
 [
  149432, 
  [
   216, 
   275, 
   {
    "quote_id": 149165, 
    "author": "Easyrider"
   }
  ]
 ], 
 [
  149432, 
  [
   302, 
   382, 
   {
    "quote_id": 149165, 
    "author": "Easyrider"
   }
  ]
 ], 
 [
  149432, 
  [
   1030, 
   1139, 
   {
    "quote_id": 149165, 
    "author": "Easyrider"
   }
  ]
 ], 
 [
  149432, 
  [
   1227, 
   1345, 
   {
    "quote_id": 149165, 
    "author": "Easyrider"
   }
  ]
 ], 
 [
  149432, 
  [
   1452, 
   1515, 
   {
    "quote_id": 149165, 
    "author": "Easyrider"
   }
  ]
 ], 
 [
  149432, 
  [
   1589, 
   1598, 
   {
    "author": "Easyrider"
   }
  ]
 ], 
 [
  149386, 
  [
   0, 
   142, 
   {
    "raw_data": "Easyrider", 
    "quote_id": 149365, 
    "author": "Easyrider"
   }
  ]
 ], 
 [
  149365, 
  [
   0, 
   369, 
   {
    "raw_data": "Tastyfish", 
    "quote_id": 149167, 
    "author": "Tastyfish"
   }
  ]
 ], 
 [
  153025, 
  [
   0, 
   65, 
   {
    "raw_data": "Easyrider", 
    "quote_id": 153006, 
    "author": "Easyrider"
   }
  ]
 ], 
 [
  153025, 
  [
   560, 
   650, 
   {
    "quote_id": 153006, 
    "author": "Easyrider"
   }
  ]
 ], 
 [
  153025, 
  [
   1069, 
   1105, 
   {
    "quote_id": 153006, 
    "author": "Easyrider"
   }
  ]
 ], 
 [
  148419, 
  [
   0, 
   143, 
   {
    "raw_data": "Easyrider", 
    "quote_id": 148407, 
    "author": "Easyrider"
   }
  ]
 ], 
 [
  148426, 
  [
   0, 
   732, 
   {
    "raw_data": "Big Orn", 
    "quote_id": 148264, 
    "author": "Big Orn"
   }
  ]
 ], 
 [
  153015, 
  [
   0, 
   196, 
   {
    "raw_data": "Easyrider", 
    "quote_id": 153006, 
    "author": "Easyrider"
   }
  ]
 ], 
 [
  153042, 
  [
   0, 
   196, 
   {
    "raw_data": "Easyrider", 
    "quote_id": 153006, 
    "author": "Easyrider"
   }
  ]
 ], 
 [
  148566, 
  [
   0, 
   126, 
   {
    "raw_data": "trebor", 
    "quote_id": 148362, 
    "author": "trebor"
   }
  ]
 ], 
 [
  150368, 
  [
   0, 
   144, 
   {
    "raw_data": "Easyrider", 
    "quote_id": 148407, 
    "author": "Easyrider"
   }
  ]
 ], 
 [
  152592, 
  [
   0, 
   1294, 
   {
    "raw_data": "Easyrider", 
    "quote_id": 148356, 
    "author": "Easyrider"
   }
  ]
 ], 
 [
  153064, 
  [
   0, 
   96, 
   {
    "raw_data": "Mucusaur", 
    "quote_id": 153042, 
    "author": "Mucusaur"
   }
  ]
 ], 
 [
  152806, 
  [
   0, 
   28, 
   {
    "raw_data": "Terje", 
    "quote_id": 152592, 
    "author": "Terje"
   }
  ]
 ], 
 [
  152591, 
  [
   0, 
   1799, 
   {
    "raw_data": "Orion", 
    "quote_id": 148169, 
    "author": "Orion"
   }
  ]
 ], 
 [
  153066, 
  [
   0, 
   593, 
   {
    "raw_data": "Easyrider", 
    "quote_id": 153064, 
    "author": "Easyrider"
   }
  ]
 ], 
 [
  153077, 
  [
   0, 
   102, 
   {
    "raw_data": "Easyrider", 
    "author": "Easyrider"
   }
  ]
 ], 
 [
  153068, 
  [
   0, 
   454, 
   {
    "raw_data": "Easyrider", 
    "quote_id": 153039, 
    "author": "Easyrider"
   }
  ]
 ], 
 [
  153069, 
  [
   30, 
   116, 
   {
    "raw_data": "Trebor", 
    "unknown_author": "Trebor"
   }
  ]
 ], 
 [
  153072, 
  [
   0, 
   1269, 
   {
    "raw_data": "Easyrider", 
    "author": "Easyrider"
   }
  ]
 ], 
 [
  148209, 
  [
   0, 
   430, 
   {
    "quote_id": 148187, 
    "author": "jazyjason"
   }
  ]
 ], 
 [
  153082, 
  [
   0, 
   64, 
   {
    "raw_data": "Orion", 
    "quote_id": 153077, 
    "author": "Orion"
   }
  ]
 ], 
 [
  153109, 
  [
   0, 
   583, 
   {
    "raw_data": "Easyrider", 
    "quote_id": 153082, 
    "author": "Easyrider"
   }
  ]
 ]
]