[
 [
  314551, 
  [
   131, 
   182, 
   {
    "url": "http://www.msnbc.msn.com/id/20010696/site/newsweek/"
   }
  ]
 ], 
 [
  315090, 
  [
   131, 
   182, 
   {
    "url": "http://www.msnbc.msn.com/id/20010696/site/newsweek/"
   }
  ]
 ], 
 [
  275785, 
  [
   131, 
   182, 
   {
    "url": "http://www.msnbc.msn.com/id/20010696/site/newsweek/"
   }
  ]
 ], 
 [
  280916, 
  [
   259, 
   483, 
   {
    "url": "http://64.233.169.104/search?q=cache:Tbf49sGpCd8J:www.leg.state.co.us/2000/inetcbill.nsf/billcontainers/D8420BD4B64A59558725685E007078C3/%24FILE/HB1231_r2.pdf+prison+sentences+unborn&hl=en&ct=clnk&cd=6&gl=us&client=firefox-a"
   }
  ]
 ], 
 [
  280916, 
  [
   692, 
   881, 
   {
    "url": "http://64.233.169.104/search?q=cache:fRajN7udMhgJ:www.leg.state.or.us/press_releases/minnis_speaker_051205.pdf+unborn+child+killed+prison+sentences&hl=en&ct=clnk&cd=4&gl=us&client=firefox-a"
   }
  ]
 ], 
 [
  280916, 
  [
   954, 
   1004, 
   {
    "url": "http://www.lifesite.net/ldn/2004/may/04051902.html"
   }
  ]
 ], 
 [
  280918, 
  [
   259, 
   483, 
   {
    "url": "http://64.233.169.104/search?q=cache:Tbf49sGpCd8J:www.leg.state.co.us/2000/inetcbill.nsf/billcontainers/D8420BD4B64A59558725685E007078C3/%24FILE/HB1231_r2.pdf+prison+sentences+unborn&hl=en&ct=clnk&cd=6&gl=us&client=firefox-a"
   }
  ]
 ], 
 [
  280918, 
  [
   692, 
   881, 
   {
    "url": "http://64.233.169.104/search?q=cache:fRajN7udMhgJ:www.leg.state.or.us/press_releases/minnis_speaker_051205.pdf+unborn+child+killed+prison+sentences&hl=en&ct=clnk&cd=4&gl=us&client=firefox-a"
   }
  ]
 ], 
 [
  280918, 
  [
   954, 
   1004, 
   {
    "url": "http://www.lifesite.net/ldn/2004/may/04051902.html"
   }
  ]
 ], 
 [
  275848, 
  [
   131, 
   182, 
   {
    "url": "http://www.msnbc.msn.com/id/20010696/site/newsweek/"
   }
  ]
 ], 
 [
  275901, 
  [
   12, 
   16, 
   {
    "url": "&quot;http://www.youtube.com/watch?v=Uk6t_tdOkwo&quot;", 
    "raw_data": "&quot;http://www.youtube.com/watch?v=Uk6t_tdOkwo&quot;"
   }
  ]
 ]
]