[
 [
  374531, 
  [
   0, 
   3, 
   {
    "category": "bold"
   }
  ]
 ], 
 [
  374531, 
  [
   30, 
   34, 
   {
    "category": "bold"
   }
  ]
 ], 
 [
  374531, 
  [
   533, 
   537, 
   {
    "category": "size", 
    "raw_data": "&quot;4&quot;"
   }
  ]
 ], 
 [
  374531, 
  [
   533, 
   537, 
   {
    "category": "bold"
   }
  ]
 ], 
 [
  374536, 
  [
   0, 
   62, 
   {
    "category": "bold"
   }
  ]
 ], 
 [
  374474, 
  [
   66, 
   69, 
   {
    "category": "bold"
   }
  ]
 ], 
 [
  374474, 
  [
   96, 
   100, 
   {
    "category": "bold"
   }
  ]
 ], 
 [
  374481, 
  [
   0, 
   3, 
   {
    "category": "bold"
   }
  ]
 ], 
 [
  374481, 
  [
   30, 
   34, 
   {
    "category": "bold"
   }
  ]
 ], 
 [
  375412, 
  [
   66, 
   69, 
   {
    "category": "bold"
   }
  ]
 ], 
 [
  375412, 
  [
   127, 
   131, 
   {
    "category": "bold"
   }
  ]
 ]
]