[
 [
  392034, 
  [
   282, 
   288, 
   {
    "category": "italic"
   }
  ]
 ], 
 [
  392034, 
  [
   1529, 
   7326, 
   {
    "category": "color", 
    "raw_data": "&quot;DarkRed&quot;"
   }
  ]
 ], 
 [
  392034, 
  [
   1529, 
   7326, 
   {
    "category": "indent"
   }
  ]
 ], 
 [
  392043, 
  [
   669, 
   717, 
   {
    "category": "bold"
   }
  ]
 ], 
 [
  391889, 
  [
   379, 
   455, 
   {
    "category": "bold"
   }
  ]
 ], 
 [
  391706, 
  [
   0, 
   30, 
   {
    "category": "bold"
   }
  ]
 ], 
 [
  391934, 
  [
   207, 
   283, 
   {
    "category": "bold"
   }
  ]
 ], 
 [
  391999, 
  [
   282, 
   288, 
   {
    "category": "italic"
   }
  ]
 ]
]