[
 [
  110658, 
  [
   966, 
   1098, 
   {
    "category": "bold"
   }
  ]
 ], 
 [
  110658, 
  [
   1525, 
   1543, 
   {
    "category": "italic"
   }
  ]
 ], 
 [
  110658, 
  [
   1358, 
   1675, 
   {
    "category": "bold"
   }
  ]
 ], 
 [
  110658, 
  [
   1877, 
   1880, 
   {
    "category": "bold"
   }
  ]
 ], 
 [
  87840, 
  [
   306, 
   534, 
   {
    "category": "bold"
   }
  ]
 ], 
 [
  87840, 
  [
   555, 
   634, 
   {
    "category": "bold"
   }
  ]
 ], 
 [
  87840, 
  [
   658, 
   1129, 
   {
    "category": "bold"
   }
  ]
 ], 
 [
  87840, 
  [
   1148, 
   1275, 
   {
    "category": "bold"
   }
  ]
 ], 
 [
  87840, 
  [
   1295, 
   1394, 
   {
    "category": "bold"
   }
  ]
 ], 
 [
  87840, 
  [
   1413, 
   1443, 
   {
    "category": "bold"
   }
  ]
 ], 
 [
  87840, 
  [
   1461, 
   1483, 
   {
    "category": "bold"
   }
  ]
 ], 
 [
  109665, 
  [
   501, 
   506, 
   {
    "category": "bold"
   }
  ]
 ], 
 [
  109665, 
  [
   603, 
   682, 
   {
    "category": "bold"
   }
  ]
 ], 
 [
  109665, 
  [
   701, 
   828, 
   {
    "category": "bold"
   }
  ]
 ], 
 [
  109665, 
  [
   848, 
   947, 
   {
    "category": "bold"
   }
  ]
 ], 
 [
  109665, 
  [
   966, 
   996, 
   {
    "category": "bold"
   }
  ]
 ], 
 [
  109665, 
  [
   1014, 
   1036, 
   {
    "category": "bold"
   }
  ]
 ], 
 [
  91863, 
  [
   802, 
   805, 
   {
    "category": "italic"
   }
  ]
 ], 
 [
  91863, 
  [
   2748, 
   2832, 
   {
    "category": "color", 
    "raw_data": "RoyalBlue"
   }
  ]
 ], 
 [
  91863, 
  [
   3229, 
   3486, 
   {
    "category": "color", 
    "raw_data": "RoyalBlue"
   }
  ]
 ], 
 [
  91863, 
  [
   3681, 
   3801, 
   {
    "category": "italic"
   }
  ]
 ], 
 [
  91863, 
  [
   4188, 
   4262, 
   {
    "category": "color", 
    "raw_data": "RoyalBlue"
   }
  ]
 ], 
 [
  91863, 
  [
   4651, 
   4767, 
   {
    "category": "color", 
    "raw_data": "RoyalBlue"
   }
  ]
 ], 
 [
  109285, 
  [
   500, 
   503, 
   {
    "category": "italic"
   }
  ]
 ], 
 [
  109305, 
  [
   232, 
   236, 
   {
    "category": "italic"
   }
  ]
 ], 
 [
  109305, 
  [
   264, 
   276, 
   {
    "category": "italic"
   }
  ]
 ], 
 [
  109305, 
  [
   438, 
   441, 
   {
    "category": "italic"
   }
  ]
 ]
]