[
 [
  177157, 
  [
   168, 
   171, 
   {
    "category": "italic"
   }
  ]
 ], 
 [
  177081, 
  [
   143, 
   147, 
   {
    "category": "italic"
   }
  ]
 ], 
 [
  178884, 
  [
   430, 
   438, 
   {
    "category": "italic"
   }
  ]
 ], 
 [
  178831, 
  [
   1171, 
   1197, 
   {
    "category": "italic"
   }
  ]
 ], 
 [
  178747, 
  [
   2753, 
   2779, 
   {
    "category": "italic"
   }
  ]
 ], 
 [
  177139, 
  [
   819, 
   823, 
   {
    "category": "italic"
   }
  ]
 ], 
 [
  177139, 
  [
   860, 
   889, 
   {
    "category": "bold"
   }
  ]
 ], 
 [
  177142, 
  [
   69, 
   73, 
   {
    "category": "italic"
   }
  ]
 ], 
 [
  177142, 
  [
   110, 
   139, 
   {
    "category": "bold"
   }
  ]
 ], 
 [
  177147, 
  [
   364, 
   368, 
   {
    "category": "italic"
   }
  ]
 ], 
 [
  177147, 
  [
   405, 
   434, 
   {
    "category": "bold"
   }
  ]
 ], 
 [
  177150, 
  [
   234, 
   237, 
   {
    "category": "italic"
   }
  ]
 ]
]