[
 [
  264576, 
  [
   0, 
   74, 
   {
    "category": "bold"
   }
  ]
 ], 
 [
  264483, 
  [
   297, 
   376, 
   {
    "category": "color", 
    "raw_data": "&quot;navy&quot;"
   }
  ]
 ], 
 [
  264483, 
  [
   1779, 
   2363, 
   {
    "category": "color", 
    "raw_data": "&quot;Navy&quot;"
   }
  ]
 ], 
 [
  264483, 
  [
   1506, 
   4176, 
   {
    "category": "color", 
    "raw_data": "&quot;navy&quot;"
   }
  ]
 ], 
 [
  264483, 
  [
   4565, 
   4689, 
   {
    "category": "bold"
   }
  ]
 ], 
 [
  264483, 
  [
   5270, 
   5276, 
   {
    "category": "italic"
   }
  ]
 ], 
 [
  264483, 
  [
   5171, 
   5331, 
   {
    "category": "bold"
   }
  ]
 ], 
 [
  264483, 
  [
   5168, 
   5331, 
   {
    "category": "color", 
    "raw_data": "&quot;Red&quot;"
   }
  ]
 ], 
 [
  264483, 
  [
   4694, 
   5376, 
   {
    "category": "color", 
    "raw_data": "&quot;Navy&quot;"
   }
  ]
 ], 
 [
  264483, 
  [
   5380, 
   6131, 
   {
    "category": "color", 
    "raw_data": "&quot;Navy&quot;"
   }
  ]
 ], 
 [
  264483, 
  [
   6538, 
   6544, 
   {
    "category": "italic"
   }
  ]
 ], 
 [
  264483, 
  [
   6439, 
   6599, 
   {
    "category": "bold"
   }
  ]
 ], 
 [
  264483, 
  [
   6135, 
   6644, 
   {
    "category": "color", 
    "raw_data": "&quot;Navy&quot;"
   }
  ]
 ], 
 [
  264483, 
  [
   6648, 
   14762, 
   {
    "category": "color", 
    "raw_data": "&quot;navy&quot;"
   }
  ]
 ], 
 [
  264874, 
  [
   4578, 
   4635, 
   {
    "category": "bold"
   }
  ]
 ], 
 [
  264874, 
  [
   5373, 
   5387, 
   {
    "category": "bold"
   }
  ]
 ], 
 [
  264874, 
  [
   5462, 
   5480, 
   {
    "category": "bold"
   }
  ]
 ], 
 [
  264874, 
  [
   6315, 
   6324, 
   {
    "category": "underline"
   }
  ]
 ], 
 [
  264440, 
  [
   533, 
   649, 
   {
    "category": "size", 
    "raw_data": "&quot;5&quot;"
   }
  ]
 ], 
 [
  264440, 
  [
   3147, 
   3153, 
   {
    "category": "underline"
   }
  ]
 ], 
 [
  264440, 
  [
   3122, 
   3153, 
   {
    "category": "bold"
   }
  ]
 ], 
 [
  264440, 
  [
   14562, 
   14686, 
   {
    "category": "bold"
   }
  ]
 ], 
 [
  264537, 
  [
   956, 
   969, 
   {
    "category": "italic"
   }
  ]
 ], 
 [
  264537, 
  [
   1025, 
   1032, 
   {
    "category": "italic"
   }
  ]
 ], 
 [
  264537, 
  [
   2460, 
   2609, 
   {
    "category": "underline"
   }
  ]
 ], 
 [
  264537, 
  [
   2460, 
   2609, 
   {
    "category": "italic"
   }
  ]
 ], 
 [
  264537, 
  [
   2460, 
   2609, 
   {
    "category": "bold"
   }
  ]
 ], 
 [
  264537, 
  [
   5355, 
   5360, 
   {
    "category": "italic"
   }
  ]
 ]
]